mars_text_embedding_sdk_python/__init__.py
mars_text_embedding_sdk_python-0.2.6.dist-info/METADATA
mars_text_embedding_sdk_python-0.2.6.dist-info/WHEEL
mars_text_embedding_sdk_python-0.2.6.dist-info/RECORD
